backup_collector/__init__.py
backup_collector/__main__.py
backup_collector/backup_worker.py
backup_collector/dbdata.py
backup_collector/dbsteps.py
backup_collector/services/backup_collector.env
backup_collector/services/backup_collector.env.tpl
backup_collector/services/backup_collector.service
backup_collector/services/backup_collector.service.tpl
backup_collector/services/build_service.sh
backup_collector/settings_manager.py
backup_collector-1.0.0.dist-info/METADATA
backup_collector-1.0.0.dist-info/entry_points.txt
backup_collector-1.0.0.dist-info/WHEEL
backup_collector-1.0.0.dist-info/RECORD
