Metadata-Version: 2.1
Name: backup-collector
Version: 1.0.0
Summary: 
Author: David Pineda
Author-email: dahalpi@gmail.com
Requires-Python: >=3.9,<4.0
Classifier: Programming Language :: Python :: 3
Classifier: Programming Language :: Python :: 3.9
Classifier: Programming Language :: Python :: 3.10
Classifier: Programming Language :: Python :: 3.11
Requires-Dist: dacite (>=1.6.0,<2.0.0)
Requires-Dist: networktools (>=1.5.1,<2.0.0)
Requires-Dist: numpy (>=1.23.4,<2.0.0)
Requires-Dist: tasktools (>=1.1.69,<2.0.0)
Requires-Dist: tomli (>=2.0.1,<3.0.0)
Requires-Dist: typer (>=0.6.1,<0.7.0)
Requires-Dist: watchdog (>=2.1.9,<3.0.0)
